astropy_changelog/__init__.py
astropy_changelog/core.py
astropy_changelog/rst_parser.py
astropy_changelog/tests/__init__.py
astropy_changelog/tests/test_rst_parser.py
astropy_changelog/tests/data/changes_core.rst
astropy_changelog/tests/data/changes_helpers.rst
astropy_changelog-0.1.dist-info/METADATA
astropy_changelog-0.1.dist-info/RECORD
astropy_changelog-0.1.dist-info/WHEEL
astropy_changelog-0.1.dist-info/top_level.txt
