Metadata-Version: 2.1
Name: astropy-changelog
Version: 0.1
Summary: Helpers for parsing astropy changelogs
Home-page: https://github.com/astrofrog/astropy-changelog
Author: Thomas Robitaille
Author-email: thomas.robitaille@gmail.com
License: UNKNOWN
Platform: UNKNOWN
Provides-Extra: test
Requires-Dist: docutils
Provides-Extra: test
Requires-Dist: pytest (>=3.5); extra == 'test'
Requires-Dist: pytest-flake8; extra == 'test'
Requires-Dist: pytest-cov; extra == 'test'
Requires-Dist: codecov; extra == 'test'
